bovespa2csv/BovespaParser.py
bovespa2csv/__init__.py
bovespa2csv/parse_file.py
bovespa2csv/util.py
bovespa2csv-0.0.2.dist-info/METADATA
bovespa2csv-0.0.2.dist-info/RECORD
bovespa2csv-0.0.2.dist-info/WHEEL
bovespa2csv-0.0.2.dist-info/top_level.txt
tests/2csv_tests.py
tests/__init__.py
