Metadata-Version: 2.1
Name: bovespa2csv
Version: 0.0.2
Summary: Parser for Bovespa data
Home-page: https://github.com/felipessalvatore/bovespa2csv
Author: Felipe Salvatore
Author-email: felipessalvador@gmail.com
License: MIT
Keywords: bovespa,parsercsv,excel
Platform: UNKNOWN
Classifier: Programming Language :: Python :: 3
Classifier: License :: OSI Approved :: MIT License
Classifier: Operating System :: OS Independent
